NetkillerFreebsdFix1/README.md
NetkillerFreebsdFix1/__init__.py
NetkillerFreebsdFix1/__main__.py
NetkillerFreebsdFix1/file.epub
NetkillerFreebsdFix1/index.html
NetkillerFreebsdFix1/css/__init__.py
NetkillerFreebsdFix1/css/annotations.css
NetkillerFreebsdFix1/css/main.css
NetkillerFreebsdFix1/css/normalize.css
NetkillerFreebsdFix1/css/popup.css
NetkillerFreebsdFix1/font/__init__.py
NetkillerFreebsdFix1/font/fontello.eot
NetkillerFreebsdFix1/font/fontello.svg
NetkillerFreebsdFix1/font/fontello.ttf
NetkillerFreebsdFix1/font/fontello.woff
NetkillerFreebsdFix1/img/__init__.py
NetkillerFreebsdFix1/img/annotator-glyph-sprite.png
NetkillerFreebsdFix1/img/annotator-icon-sprite.png
NetkillerFreebsdFix1/img/apple-touch-icon.png
NetkillerFreebsdFix1/img/cancelfullscreen.png
NetkillerFreebsdFix1/img/close.png
NetkillerFreebsdFix1/img/fullscreen.png
NetkillerFreebsdFix1/img/loader.gif
NetkillerFreebsdFix1/img/menu-icon.png
NetkillerFreebsdFix1/img/save.png
NetkillerFreebsdFix1/img/saved.png
NetkillerFreebsdFix1/img/settings-s.png
NetkillerFreebsdFix1/img/settings.png
NetkillerFreebsdFix1/img/star.png
NetkillerFreebsdFix1/js/__init__.py
NetkillerFreebsdFix1/js/epub.js
NetkillerFreebsdFix1/js/epub.min.js
NetkillerFreebsdFix1/js/epub.min.map
NetkillerFreebsdFix1/js/hooks.min.js
NetkillerFreebsdFix1/js/hooks.min.map
NetkillerFreebsdFix1/js/reader.js
NetkillerFreebsdFix1/js/reader.js.map
NetkillerFreebsdFix1/js/reader.min.js
NetkillerFreebsdFix1/js/reader.min.map
NetkillerFreebsdFix1/js/hooks/__init__.py
NetkillerFreebsdFix1/js/hooks/extensions/__init__.py
NetkillerFreebsdFix1/js/hooks/extensions/highlight.js
NetkillerFreebsdFix1/js/libs/__init__.py
NetkillerFreebsdFix1/js/libs/jquery.min.js
NetkillerFreebsdFix1/js/libs/localforage.min.js
NetkillerFreebsdFix1/js/libs/screenfull.js
NetkillerFreebsdFix1/js/libs/screenfull.min.js
NetkillerFreebsdFix1/js/libs/zip.min.js
NetkillerFreebsdFix1/js/plugins/__init__.py
NetkillerFreebsdFix1/js/plugins/hypothesis.js
netkiller_freebsd_fix1-2025.3.24.1.dist-info/METADATA
netkiller_freebsd_fix1-2025.3.24.1.dist-info/WHEEL
netkiller_freebsd_fix1-2025.3.24.1.dist-info/entry_points.txt
netkiller_freebsd_fix1-2025.3.24.1.dist-info/top_level.txt
netkiller_freebsd_fix1-2025.3.24.1.dist-info/RECORD
